spacy_och/__init__.py
spacy_och/config.cfg
spacy_och/examples.py
spacy_och/lex_attrs.py
spacy_och/stop_words.py
spacy_och/lookups/__init__.py
spacy_och/lookups/och_numbers_lookup.json
spacy_och/lookups/och_phonemes_lookup.json
spacy_och/lookups/och_pinyin_lookup.json
spacy_och/lookups/och_variants_lookup.json
spacy_och-0.1.2.dist-info/LICENSE
spacy_och-0.1.2.dist-info/METADATA
spacy_och-0.1.2.dist-info/WHEEL
spacy_och-0.1.2.dist-info/entry_points.txt
spacy_och-0.1.2.dist-info/top_level.txt
spacy_och-0.1.2.dist-info/RECORD
