Metadata-Version: 2.1
Name: spacy-och
Version: 0.1.2
Summary: the Old Chinese language for spaCy
Home-page: https://github.com/direct-phonology/spacy-och
Author: Nick Budak
Author-email: budak@stanford.edu
License: MIT
Platform: UNKNOWN
Classifier: License :: OSI Approved :: MIT License
Classifier: Natural Language :: Chinese (Traditional)
Classifier: Operating System :: OS Independent
Classifier: Topic :: Text Processing :: Linguistic
Classifier: Topic :: Utilities
Requires-Python: >=3.9
License-File: LICENSE
Requires-Dist: spacy (>=3)
Provides-Extra: dev
Requires-Dist: pre-commit ; extra == 'dev'
Requires-Dist: isort ; extra == 'dev'
Requires-Dist: black ; extra == 'dev'
